django_filehub-3.2.2.dist-info/licenses/AUTHORS
django_filehub-3.2.2.dist-info/licenses/LICENSE
filehub/__init__.py
filehub/admin.py
filehub/apps.py
filehub/core.py
filehub/fields.py
filehub/forms.py
filehub/models.py
filehub/serializers.py
filehub/settings.py
filehub/signals.py
filehub/tests.py
filehub/urls.py
filehub/utils.py
filehub/views.py
filehub/widgets.py
filehub/migrations/0001_initial.py
filehub/migrations/0002_initial.py
filehub/migrations/__init__.py
filehub/static/filehub/main.js
filehub/static/filehub/style.css
filehub/static/filehub/widget.css
filehub/static/filehub/widget.js
filehub/static/filehub/tinymce/plugin.js
filehub/templates/filehub/filehub_list.html
filehub/templates/filehub/includes/content-header.html
filehub/templates/filehub/includes/content.html
filehub/templates/filehub/includes/modals.html
filehub/templates/filehub/includes/top-header.html
filehub/templates/filehub/includes/tree.html
filehub/templates/filehub/widgets/file_picker.html
filehub/templates/filehub/widgets/gallery_picker.html
filehub/templates/filehub/widgets/image_picker.html
filehub/templatetags/filehub.py
django_filehub-3.2.2.dist-info/METADATA
django_filehub-3.2.2.dist-info/WHEEL
django_filehub-3.2.2.dist-info/top_level.txt
django_filehub-3.2.2.dist-info/RECORD
