Metadata-Version: 2.4
Name: django_filehub
Version: 3.2.2
Summary: FileHub is a Django-based file management app that simplifies file handling within your Django projects. It supports file uploads, storage, and retrieval, making it easy to integrate robust file management features into your applications.
Author: Suresh Chand
Author-email: scthakuri12a@gmail.com
License: BSD
Project-URL: Bug Reports, https://github.com/scthakuri/django-filehub/issues
Project-URL: Source, https://github.com/scthakuri/django-filehub
Classifier: Programming Language :: Python :: 3
Classifier: Framework :: Django
Classifier: Environment :: Web Environment
Classifier: Intended Audience :: Developers
Classifier: Operating System :: OS Independent
Classifier: Development Status :: 5 - Production/Stable
Classifier: License :: OSI Approved :: BSD License
License-File: LICENSE
License-File: AUTHORS
Requires-Dist: django
Requires-Dist: requests
Requires-Dist: pillow
Requires-Dist: standard-imghdr
Dynamic: author
Dynamic: author-email
Dynamic: classifier
Dynamic: description
Dynamic: description-content-type
Dynamic: license
Dynamic: license-file
Dynamic: project-url
Dynamic: requires-dist
Dynamic: summary
